[
  {
    "name" : "MongoDB Tutorial1",
    "author" : "velopert1",
    "published_date": "2017-04-01"
  },
  {
    "name" : "MongoDB Tutorial2",
    "author" : "velopert2",
    "published_date": "2017-04-02"
  },
  {
    "name" : "MongoDB Tutorial3",
    "author" : "velopert3",
    "published_date": "2017-04-03"
  },
  {
    "name" : "MongoDB Tutorial4",
    "author" : "velopert4",
    "published_date": "2017-04-04"
  },
  {
    "name" : "MongoDB Tutorial5",
    "author" : "velopert5",
    "published_date": "2017-04-05"
  }

]